streamlit_chat/__init__.py
streamlit_chat/frontend/dist/index.html
streamlit_chat/frontend/dist/assets/KaTeX_AMS-Regular-0cdd387c.woff2
streamlit_chat/frontend/dist/assets/KaTeX_AMS-Regular-30da91e8.woff
streamlit_chat/frontend/dist/assets/KaTeX_AMS-Regular-68534840.ttf
streamlit_chat/frontend/dist/assets/KaTeX_Caligraphic-Bold-07d8e303.ttf
streamlit_chat/frontend/dist/assets/KaTeX_Caligraphic-Bold-1ae6bd74.woff
streamlit_chat/frontend/dist/assets/KaTeX_Caligraphic-Bold-de7701e4.woff2
streamlit_chat/frontend/dist/assets/KaTeX_Caligraphic-Regular-3398dd02.woff
streamlit_chat/frontend/dist/assets/KaTeX_Caligraphic-Regular-5d53e70a.woff2
streamlit_chat/frontend/dist/assets/KaTeX_Caligraphic-Regular-ed0b7437.ttf
streamlit_chat/frontend/dist/assets/KaTeX_Fraktur-Bold-74444efd.woff2
streamlit_chat/frontend/dist/assets/KaTeX_Fraktur-Bold-9163df9c.ttf
streamlit_chat/frontend/dist/assets/KaTeX_Fraktur-Bold-9be7ceb8.woff
streamlit_chat/frontend/dist/assets/KaTeX_Fraktur-Regular-1e6f9579.ttf
streamlit_chat/frontend/dist/assets/KaTeX_Fraktur-Regular-51814d27.woff2
streamlit_chat/frontend/dist/assets/KaTeX_Fraktur-Regular-5e28753b.woff
streamlit_chat/frontend/dist/assets/KaTeX_Main-Bold-0f60d1b8.woff2
streamlit_chat/frontend/dist/assets/KaTeX_Main-Bold-138ac28d.ttf
streamlit_chat/frontend/dist/assets/KaTeX_Main-Bold-c76c5d69.woff
streamlit_chat/frontend/dist/assets/KaTeX_Main-BoldItalic-70ee1f64.ttf
streamlit_chat/frontend/dist/assets/KaTeX_Main-BoldItalic-99cd42a3.woff2
streamlit_chat/frontend/dist/assets/KaTeX_Main-BoldItalic-a6f7ec0d.woff
streamlit_chat/frontend/dist/assets/KaTeX_Main-Italic-0d85ae7c.ttf
streamlit_chat/frontend/dist/assets/KaTeX_Main-Italic-97479ca6.woff2
streamlit_chat/frontend/dist/assets/KaTeX_Main-Italic-f1d6ef86.woff
streamlit_chat/frontend/dist/assets/KaTeX_Main-Regular-c2342cd8.woff2
streamlit_chat/frontend/dist/assets/KaTeX_Main-Regular-c6368d87.woff
streamlit_chat/frontend/dist/assets/KaTeX_Main-Regular-d0332f52.ttf
streamlit_chat-0.1.1.dist-info/LICENSE
streamlit_chat-0.1.1.dist-info/METADATA
streamlit_chat-0.1.1.dist-info/WHEEL
streamlit_chat-0.1.1.dist-info/top_level.txt
streamlit_chat-0.1.1.dist-info/RECORD
