Metadata-Version: 2.1
Name: streamlit-chat
Version: 0.1.1
Summary: A streamlit component, to make chatbots
Home-page: https://github.com/AI-Yash/st-chat
Author: Yash Pravin Pawar, Yash Vardhan Kapil
Author-email: yashpawarp@gmail.com
License: UNKNOWN
Keywords: chat streamlit streamlit-component
Platform: UNKNOWN
Classifier: Programming Language :: Python :: 3
Classifier: Operating System :: OS Independent
Requires-Python: >=3.6
